appstore_profile_scraper/__init__.py
appstore_profile_scraper/__version__.py
appstore_profile_scraper/app_store_base.py
appstore_profile_scraper/app_store_profile.py
appstore_profile_scraper-0.0.10.dist-info/METADATA
appstore_profile_scraper-0.0.10.dist-info/WHEEL
appstore_profile_scraper-0.0.10.dist-info/top_level.txt
appstore_profile_scraper-0.0.10.dist-info/RECORD
