Metadata-Version: 2.1
Name: appstore-profile-scraper
Version: 0.0.10
Summary: App Store Profile Information Scraper
Home-page: https://github.com/KeremDlkmn/appstore-profile-scraper
Author: Kerem Delikmen
License: MIT
Project-URL: Source, https://github.com/KeremDlkmn/appstore-profile-scraper
Keywords: app store,ios,ios apps,profile,app profile,app title,scraping,scraper
Platform: UNKNOWN
Classifier: Intended Audience :: Developers
Classifier: License :: OSI Approved :: MIT License
Classifier: Natural Language :: English
Classifier: Operating System :: OS Independent
Classifier: Programming Language :: Python :: 3
Classifier: Programming Language :: Python :: 3.6
Classifier: Programming Language :: Python :: 3.7
Classifier: Programming Language :: Python :: 3.8
Classifier: Topic :: Internet :: WWW/HTTP
Classifier: Topic :: Scientific/Engineering :: Information Analysis
Requires-Python: >=3.6
Requires-Dist: requests (==2.23.0)
